xyzpy/__init__.py
xyzpy/_version.py
xyzpy/manage.py
xyzpy/utils.py
xyzpy/gen/__init__.py
xyzpy/gen/case_runner.py
xyzpy/gen/combo_runner.py
xyzpy/gen/cropping.py
xyzpy/gen/farming.py
xyzpy/gen/prepare.py
xyzpy/plot/__init__.py
xyzpy/plot/color.py
xyzpy/plot/core.py
xyzpy/plot/marker.py
xyzpy/plot/plotter_bokeh.py
xyzpy/plot/plotter_matplotlib.py
xyzpy/plot/xyz_cmaps.py
xyzpy-1.2.1.dist-info/LICENSE
xyzpy-1.2.1.dist-info/METADATA
xyzpy-1.2.1.dist-info/WHEEL
xyzpy-1.2.1.dist-info/top_level.txt
xyzpy-1.2.1.dist-info/RECORD
