Metadata-Version: 2.1
Name: xyzpy
Version: 1.2.1
Summary: Easily generate large parameter space data
Home-page: http://xyzpy.readthedocs.io
Author: Johnnie Gray
Author-email: johnniemcgray@gmail.com
License: MIT
Platform: UNKNOWN
Classifier: Development Status :: 3 - Alpha
Classifier: License :: OSI Approved :: MIT License
Classifier: Programming Language :: Python
Classifier: Programming Language :: Python :: 3
Classifier: Programming Language :: Python :: 3.5
Classifier: Programming Language :: Python :: 3.6
Classifier: Programming Language :: Python :: 3.7
Classifier: Programming Language :: Python :: 3.8
Requires-Python: >=3.5
Requires-Dist: numpy (>=1.10.0)
Requires-Dist: dask (>=0.11.1)
Requires-Dist: xarray (>=0.9.0)
Requires-Dist: pandas (>=0.20)
Requires-Dist: h5py (>=2.6.0)
Requires-Dist: h5netcdf (>=0.2.2)
Requires-Dist: joblib (>=0.12)
Requires-Dist: tqdm (>=4.7.6)
Provides-Extra: docs
Requires-Dist: matplotlib ; extra == 'docs'
Requires-Dist: bokeh ; extra == 'docs'
Requires-Dist: sphinx ; extra == 'docs'
Requires-Dist: sphinx-book-theme (>=0.1) ; extra == 'docs'
Requires-Dist: nbsphinx ; extra == 'docs'
Requires-Dist: ipython ; extra == 'docs'
Provides-Extra: plotting
Requires-Dist: matplotlib ; extra == 'plotting'
Requires-Dist: bokeh ; extra == 'plotting'
Provides-Extra: tests
Requires-Dist: coverage ; extra == 'tests'
Requires-Dist: pytest ; extra == 'tests'
Requires-Dist: pytest-cov ; extra == 'tests'
